byted_overpass_motor_bizlog_collector/__init__.py
byted_overpass_motor_bizlog_collector-0.0.1.dist-info/METADATA
byted_overpass_motor_bizlog_collector-0.0.1.dist-info/WHEEL
byted_overpass_motor_bizlog_collector-0.0.1.dist-info/top_level.txt
byted_overpass_motor_bizlog_collector-0.0.1.dist-info/RECORD
