Metadata-Version: 2.1
Name: byted-overpass-motor-bizlog-collector
Version: 0.0.1
Summary: A simple package named byted_overpass_motor_bizlog_collector
Home-page: https://github.com/artifact/byted_overpass_motor_bizlog_collector.git
Author: artifact
Author-email: artifact@example.com
License: UNKNOWN
Platform: UNKNOWN
Classifier: Programming Language :: Python :: 3
Classifier: License :: OSI Approved :: MIT License
Classifier: Operating System :: OS Independent
